{
  "debug": true,
  "verbose": true,
  "autoDate": true,
  "inputDirectory": "chapters",
  "inputFiles": [
    "Index.md",
    "Introduction-and-Motivation.md",
    "Conformance.md",
    "Terminology.md",
    "Syntax.md",
    "CRUD-Operations.md",
    "Update-Beacons.md",
    "Security-Considerations.md",
    "Privacy-Considerations.md",
    "References.md",
    "Appendix.md"
  ],
  "cssFiles": [
    "index.css"
  ],
  "outputDirectory": "_site",
  "cleanOutput": true,
  "outputFile": "index.html"
}
